computed_property/__init__.py
computed_property/fields.py
django_computed_property-0.3.0.dist-info/AUTHORS
django_computed_property-0.3.0.dist-info/LICENSE
django_computed_property-0.3.0.dist-info/METADATA
django_computed_property-0.3.0.dist-info/WHEEL
django_computed_property-0.3.0.dist-info/top_level.txt
django_computed_property-0.3.0.dist-info/RECORD
